temper_windows/__init__.py
temper_windows/temper_windows.py
temper_windows-1.0.1.dist-info/LICENSE
temper_windows-1.0.1.dist-info/METADATA
temper_windows-1.0.1.dist-info/WHEEL
temper_windows-1.0.1.dist-info/top_level.txt
temper_windows-1.0.1.dist-info/RECORD
