Metadata-Version: 2.1
Name: temper-windows
Version: 1.0.1
Summary: Gets the temperature from a Temper USB thermometer on windows.
Home-page: https://github.com/tom-churchill/temper-windows
Author: Tom Churchill
Author-email: tom@tomchurchill.co.uk 
License: UNKNOWN
Platform: UNKNOWN
Classifier: Programming Language :: Python :: 3
Classifier: Programming Language :: Python :: 3.6
Classifier: Programming Language :: Python :: 2
Classifier: Programming Language :: Python :: 2.7
Classifier: License :: OSI Approved :: MIT License
Classifier: Operating System :: Microsoft :: Windows
Requires-Dist: pywinusb (>=0.3.2)
